wbs/__init__.py
wbs/coding_scheme.py
wbs/element.py
wbs/node.py
wbs-1.0.0.dist-info/LICENSE
wbs-1.0.0.dist-info/METADATA
wbs-1.0.0.dist-info/WHEEL
wbs-1.0.0.dist-info/top_level.txt
wbs-1.0.0.dist-info/RECORD
