Metadata-Version: 2.1
Name: wbs
Version: 1.0.0
Summary: Work breakdown structures.
Author-email: Damien Bezborodov <dbezborodov@gmail.com>
License: BSD 3-Clause License
Project-URL: Homepage, https://github.com/bezborodow/wbs
Project-URL: Bug Tracker, https://github.com/bezborodow/wbs/issues
Project-URL: Documentation, https://wbs.readthedocs.io/en/latest/
Keywords: wbs
Classifier: Programming Language :: Python :: 3
Classifier: License :: OSI Approved :: BSD License
Classifier: Operating System :: OS Independent
Requires-Python: >=3.7
License-File: LICENSE
